ai_spine/__init__.py
ai_spine/__version__.py
ai_spine/client.py
ai_spine/constants.py
ai_spine/exceptions.py
ai_spine/models.py
ai_spine/utils.py
ai_spine_sdk-2.3.1.dist-info/licenses/LICENSE
ai_spine_sdk-2.3.1.dist-info/METADATA
ai_spine_sdk-2.3.1.dist-info/WHEEL
ai_spine_sdk-2.3.1.dist-info/entry_points.txt
ai_spine_sdk-2.3.1.dist-info/top_level.txt
ai_spine_sdk-2.3.1.dist-info/RECORD
